full_adder/code+testbench/design.v
module full_adder(
    input a,
    input b,
    input c,
    output sum,
    output carry
);
wire s1,s2,s3;
assign s1=a ^ b;
assign sum = c ^ s1;
assign s2 = s1 & c;
assign s3 = a & b;
assign carry = s2 | s3;
endmodule

full_adder/code+testbench/testbench.v
module testbench;
      reg a;
      reg b;
      reg c;
      wire carry,sum;


    full_adder uut(
            .a(a),
            .b(b),
            .c(c),
            .carry(carry),
            .sum(sum)
         );
         
        initial begin
          $dumpfile("dump.vcd");
          $dumpvars(0,testbench);
           a=0;b=0;c=0;
           #100
             a=0;b=0;c=1;
           #100
             a=0;b=1;c=0;
           #100
             a=0;b=1;c=1;
           #100
             a=1;b=0;c=0;
           #100
             a=1;b=0;c=1;
           #100
             a=1;b=1;c=0;
           #100
            a=1;b=1;c=1;
           #100
           $finish;
        end
endmodule

full_adder/simulation_vcdfile/dump.vcd
$date
	Sat Aug 24 20:30:04 2024
$end
$version
	Icarus Verilog
$end
$timescale
	1s
$end
$scope module testbench $end
$var wire 1 ! sum $end
$var wire 1 " carry $end
$var reg 1 # a $end
$var reg 1 $ b $end
$var reg 1 % c $end
$scope module uut $end
$var wire 1 # a $end
$var wire 1 $ b $end
$var wire 1 % c $end
$var wire 1 " carry $end
$var wire 1 & s1 $end
$var wire 1 ' s2 $end
$var wire 1 ( s3 $end
$var wire 1 ! sum $end
$upscope $end
$upscope $end
$enddefinitions $end
#0
$dumpvars
0(
0'
0&
0%
0$
0#
0"
0!
$end
#100
1!
1%
#200
1&
0%
1$
#300
1"
0!
1'
1%
#400
0"
1!
0'
0%
0$
1#
#500
1"
0!
1'
1%
#600
0'
0&
1(
0%
1$
#700
1!
1%
